terralab/.terralab-cli-config
terralab/__init__.py
terralab/auth_helper.py
terralab/cli.py
terralab/client.py
terralab/commands/__init__.py
terralab/commands/auth_commands.py
terralab/commands/pipeline_runs_commands.py
terralab/commands/pipelines_commands.py
terralab/commands/quotas_commands.py
terralab/config.py
terralab/constants.py
terralab/log.py
terralab/logic/__init__.py
terralab/logic/auth_logic.py
terralab/logic/pipeline_runs_logic.py
terralab/logic/pipelines_logic.py
terralab/logic/quotas_logic.py
terralab/utils.py
terralab/version_utils.py
terralab_cli-3.0.0.dist-info/METADATA
terralab_cli-3.0.0.dist-info/WHEEL
terralab_cli-3.0.0.dist-info/entry_points.txt
terralab_cli-3.0.0.dist-info/licenses/LICENSE
terralab_cli-3.0.0.dist-info/RECORD
