Metadata-Version: 2.4
Name: terralab-cli
Version: 3.0.0
Summary: Command line interface for interacting with the Terra Scientific Pipelines Service, or Teaspoons.
License-File: LICENSE
Author: Terra Scientific Services
Author-email: teaspoons-developers@broadinstitute.org
Requires-Python: >=3.12,<4.0
Classifier: Programming Language :: Python :: 3
Classifier: Programming Language :: Python :: 3.12
Classifier: Programming Language :: Python :: 3.13
Classifier: Programming Language :: Python :: 3.14
Requires-Dist: PyJWT (>=2.9.0,<3.0.0)
Requires-Dist: click (>=8.1.7,<9.0.0)
Requires-Dist: colorlog (>=6.9.0,<7.0.0)
Requires-Dist: cryptography (>=44.0.1,<45.0.0)
Requires-Dist: oauth2-cli-auth (>=1.5.0,<2.0.0)
Requires-Dist: poetry (==1.8.5)
Requires-Dist: prompt-toolkit (>=3.0.51,<4.0.0)
Requires-Dist: python-dotenv (>=1.0.1,<2.0.0)
Requires-Dist: requests (>=2.32.3,<3.0.0)
Requires-Dist: tabulate (>=0.9.0,<0.10.0)
Requires-Dist: terra-scientific-pipelines-service-api-client (==2.1.2)
Requires-Dist: tqdm (>=4.67.0,<5.0.0)
Requires-Dist: tzlocal (>=5.2,<6.0)
